{"version":1,"resource":"vscode-remote://ssh-remote%2B159.223.135.30/root/server/server.js","entries":[{"id":"4IYb.js","timestamp":1664308726117},{"id":"t5Po.js","timestamp":1664308789271},{"id":"nIbO.js","timestamp":1664309068911},{"id":"dwcM.js","timestamp":1664309140185},{"id":"e7bi.js","timestamp":1664329252470},{"id":"ZO2s.js","timestamp":1664329380013},{"id":"I9gW.js","timestamp":1664329424659},{"id":"EGqt.js","timestamp":1664329580067},{"id":"U6OY.js","timestamp":1664329737437},{"id":"e368.js","timestamp":1664329896707},{"id":"LfEq.js","timestamp":1664329913320},{"id":"6X3i.js","timestamp":1664329928694},{"id":"7muS.js","timestamp":1664330096605},{"id":"Tkic.js","timestamp":1664330659325},{"id":"BTfz.js","timestamp":1664330701854},{"id":"BOig.js","source":"undoRedo.source","timestamp":1664330854409},{"id":"JGod.js","timestamp":1664331807190},{"id":"epzb.js","timestamp":1664331833325},{"id":"a4gI.js","timestamp":1664331858638},{"id":"qCHK.js","timestamp":1664332012687},{"id":"kfMV.js","timestamp":1664332340592},{"id":"NRRN.js","timestamp":1664332443122},{"id":"NUSn.js","timestamp":1664332527018},{"id":"4GRE.js","timestamp":1664332583859},{"id":"Z6kN.js","timestamp":1664332730779},{"id":"O887.js","timestamp":1664332805884},{"id":"9U9H.js","timestamp":1664332932927},{"id":"Trmz.js","source":"undoRedo.source","timestamp":1664333100450},{"id":"1S9F.js","timestamp":1664333280087},{"id":"aD01.js","timestamp":1664333311695},{"id":"gIAt.js","timestamp":1664333340063},{"id":"yfPt.js","timestamp":1664660238846},{"id":"X4a2.js","timestamp":1664660287858},{"id":"gAIb.js","source":"undoRedo.source","timestamp":1664660296615},{"id":"wovx.js","timestamp":1664660407612},{"id":"GVaX.js","timestamp":1664660981165},{"id":"hFnr.js","timestamp":1664661115922},{"id":"lLYg.js","timestamp":1664661141729},{"id":"RTYx.js","timestamp":1664661178722},{"id":"9lfN.js","timestamp":1664661409324},{"id":"9ZGF.js","timestamp":1664661425465},{"id":"moHa.js","source":"undoRedo.source","timestamp":1664661441374},{"id":"cJ5j.js","timestamp":1664661542892},{"id":"c4Xy.js","timestamp":1664661691524},{"id":"zldy.js","timestamp":1664661731955},{"id":"E7Fh.js","timestamp":1664661762536},{"id":"NZzJ.js","timestamp":1664661824083},{"id":"RTFK.js","timestamp":1664662127517},{"id":"zgpH.js","timestamp":1664662154741},{"id":"ua1Q.js","timestamp":1664662169315}]}